{
  "title": "Ghost of Yotei: A Nova Aventura Épica da Sucker Punch para PS5",
  "publish_date": "2025-04-19",
  "content": "<p>A Sucker Punch Productions está prestes a lançar sua mais nova obra-prima exclusiva para PlayStation 5, Ghost of Yotei, sequência do aclamado Ghost of Tsushima. Ambientado em uma nova região do Japão feudal, o jogo promete expandir tudo o que tornou o original um sucesso, com um mundo ainda mais vasto e imersivo.</p><h2>Uma Nova Era, Um Novo Herói</h2><p>Ghost of Yotei nos transporta para a região norte do Japão, onde o imponente Monte Yotei serve como pano de fundo para uma nova história de honra, vingança e redenção. Jogadores assumirão o papel de um novo protagonista, enfrentando as consequências de uma invasão que ameaça destruir seu lar e seu povo.</p><p>A Sucker Punch prometeu um sistema de combate refinado, mantendo a elegância e precisão que caracterizaram o título original, mas adicionando novas técnicas e estilos de luta que refletem as tradições da nova região.</p><h2>Visuais Deslumbrantes</h2><p>Aproveitando todo o poder do PlayStation 5, Ghost of Yotei apresenta paisagens de tirar o fôlego, desde florestas nevadas até vilas tradicionais japonesas meticulosamente detalhadas. O ciclo dinâmico de dia e noite, combinado com um sistema climático avançado, cria um mundo que reage e evolui de forma orgânica.</p><p>A tecnologia de ray tracing do PS5 é utilizada para criar reflexos realistas em superfícies como lagos congelados e lâminas de katanas, enquanto o sistema háptico do DualSense promete fazer os jogadores sentirem cada impacto de espada e cada passo na neve profunda.</p><h2>Mundo Aberto Expandido</h2><p>O mapa de Ghost of Yotei será significativamente maior que o do jogo original, oferecendo uma variedade de biomas e locais para explorar. Aldeias escondidas nas montanhas, templos ancestrais e fortalezas inimigas são apenas alguns dos cenários que os jogadores poderão descobrir.</p><p>A Sucker Punch também prometeu um sistema de missões secundárias mais profundo, com histórias que se entrelaçam com a narrativa principal e personagens memoráveis que evoluem ao longo da jornada do protagonista.</p><h2>Lançamento Aguardado</h2><p>Ghost of Yotei está programado para ser lançado exclusivamente para PlayStation 5 no final de 2025, sendo um dos títulos mais aguardados da plataforma. Com sua combinação de narrativa envolvente, combate refinado e visuais deslumbrantes, o jogo promete elevar ainda mais o padrão estabelecido por seu predecessor.</p>",
  "excerpt": "Ghost of Yotei, sequência do aclamado Ghost of Tsushima, chega exclusivamente ao PlayStation 5 em 2025. Ambientado em uma nova região do Japão feudal, o jogo promete combate refinado, um mundo aberto expandido e visuais deslumbrantes que aproveitam todo o poder do console.",
  "image_path": "/images/blog/ghost_of_yotei.webp",
  "category": "PlayStation 5",
  "tags": [
    "Ghost of Yotei",
    "Sucker Punch",
    "PS5",
    "exclusivo",
    "mundo aberto",
    "Japão feudal"
  ],
  "published": true
}